{
  "games": [
    {
      "PutRequest": {
        "Item": {
          "uniqueId": {
            "S": "772104bf-046f-4c48-948f-5de57ff141c7"
          },
          "gameName": {
            "S": "Rogue Lords"
          },
          "platform": {
            "S": "Xbox One"
          },
          "gameURL": {
            "S": "https://www.trueachievements.com/game/Rogue-Lords/achievements?gamerid=428021"
          },
          "achievementsWonNoDlc": {
            "N": "19"
          },
          "maxAchievementsNoDlc": {
            "N": "35"
          },
          "achievementsWonIncludeDlc": {
            "N": "19"
          },
          "maxAchievementsIncludeDlc": {
            "N": "35"
          },
          "gamerScoreWonNoDlc": {
            "N": "585"
          },
          "maxGamerScoreNoDlc": {
            "N": "1000"
          },
          "gamerScoreWonIncludeDlc": {
            "N": "585"
          },
          "maxGamerScoreIncludeDlc": {
            "N": "1000"
          },
          "trueAchievementWonNoDlc": {
            "N": "1110"
          },
          "maxTrueAchievementNoDlc": {
            "N": "3123"
          },
          "trueAchievementWonIncludeDlc": {
            "N": "1110"
          },
          "maxTrueAchievementIncludeDlc": {
            "N": "3123"
          },
          "myCompletionPercentage": {
            "N": "54"
          },
          "completionDate": {
            "S": ""
          },
          "challengesWon": {
            "N": "0"
          },
          "maxChallenges": {
            "N": "0"
          },
          "hoursPlayed": {
            "N": "36"
          },
          "myRating": {
            "N": "0"
          },
          "siteRating": {
            "N": "3.33"
          },
          "myRatio": {
            "N": "1.9"
          },
          "siteRatio": {
            "N": "3.12"
          },
          "ownershipStatus": {
            "S": "Owned"
          },
          "playStatus": {
            "S": "Playing now"
          },
          "format": {
            "S": "Digital"
          },
          "completionEstimate": {
            "S": ""
          },
          "walkthrough": {
            "S": ""
          },
          "gameNotes": {
            "S": "None"
          },
          "contestStatus": {
            "S": "For contests"
          }
        }
      }
    },
    {
      "PutRequest": {
        "Item": {
          "uniqueId": {
            "S": "d8b136a5-cb6e-4f6d-ab5a-2123cf304c46"
          },
          "gameName": {
            "S": "Roguebook"
          },
          "platform": {
            "S": "Xbox One"
          },
          "gameURL": {
            "S": "https://www.trueachievements.com/game/Roguebook/achievements?gamerid=428021"
          },
          "achievementsWonNoDlc": {
            "N": "39"
          },
          "maxAchievementsNoDlc": {
            "N": "53"
          },
          "achievementsWonIncludeDlc": {
            "N": "43"
          },
          "maxAchievementsIncludeDlc": {
            "N": "58"
          },
          "gamerScoreWonNoDlc": {
            "N": "630"
          },
          "maxGamerScoreNoDlc": {
            "N": "1000"
          },
          "gamerScoreWonIncludeDlc": {
            "N": "700"
          },
          "maxGamerScoreIncludeDlc": {
            "N": "1100"
          },
          "trueAchievementWonNoDlc": {
            "N": "1221"
          },
          "maxTrueAchievementNoDlc": {
            "N": "3566"
          },
          "trueAchievementWonIncludeDlc": {
            "N": "1336"
          },
          "maxTrueAchievementIncludeDlc": {
            "N": "3772"
          },
          "myCompletionPercentage": {
            "N": "74"
          },
          "completionDate": {
            "S": ""
          },
          "challengesWon": {
            "N": "0"
          },
          "maxChallenges": {
            "N": "0"
          },
          "hoursPlayed": {
            "N": "61"
          },
          "myRating": {
            "N": "0"
          },
          "siteRating": {
            "N": "3.9"
          },
          "myRatio": {
            "N": "1.91"
          },
          "siteRatio": {
            "N": "3.43"
          },
          "ownershipStatus": {
            "S": "Owned"
          },
          "playStatus": {
            "S": "Playing now"
          },
          "format": {
            "S": "Digital"
          },
          "completionEstimate": {
            "S": ""
          },
          "walkthrough": {
            "S": ""
          },
          "gameNotes": {
            "S": "None"
          },
          "contestStatus": {
            "S": "For contests"
          }
        }
      }
    },
    {
      "PutRequest": {
        "Item": {
          "uniqueId": {
            "S": "34ff3bf5-2c7c-493f-a457-851d742f8ce1"
          },
          "gameName": {
            "S": "Roundguard"
          },
          "platform": {
            "S": "Xbox One"
          },
          "gameURL": {
            "S": "https://www.trueachievements.com/game/Roundguard/achievements?gamerid=428021"
          },
          "achievementsWonNoDlc": {
            "N": "45"
          },
          "maxAchievementsNoDlc": {
            "N": "45"
          },
          "achievementsWonIncludeDlc": {
            "N": "49"
          },
          "maxAchievementsIncludeDlc": {
            "N": "80"
          },
          "gamerScoreWonNoDlc": {
            "N": "1000"
          },
          "maxGamerScoreNoDlc": {
            "N": "1000"
          },
          "gamerScoreWonIncludeDlc": {
            "N": "1140"
          },
          "maxGamerScoreIncludeDlc": {
            "N": "1800"
          },
          "trueAchievementWonNoDlc": {
            "N": "1559"
          },
          "maxTrueAchievementNoDlc": {
            "N": "1559"
          },
          "trueAchievementWonIncludeDlc": {
            "N": "1879"
          },
          "maxTrueAchievementIncludeDlc": {
            "N": "5054"
          },
          "myCompletionPercentage": {
            "N": "84"
          },
          "completionDate": {
            "S": ""
          },
          "challengesWon": {
            "N": "0"
          },
          "maxChallenges": {
            "N": "0"
          },
          "hoursPlayed": {
            "N": "26"
          },
          "myRating": {
            "N": "0"
          },
          "siteRating": {
            "N": "3.99"
          },
          "myRatio": {
            "N": "1.65"
          },
          "siteRatio": {
            "N": "2.81"
          },
          "ownershipStatus": {
            "S": "Owned"
          },
          "playStatus": {
            "S": "Playing now"
          },
          "format": {
            "S": "Digital"
          },
          "completionEstimate": {
            "S": "15-20 hours"
          },
          "walkthrough": {
            "S": ""
          },
          "gameNotes": {
            "S": "None"
          },
          "contestStatus": {
            "S": "For contests"
          }
        }
      }
    },
    {
      "PutRequest": {
        "Item": {
          "uniqueId": {
            "S": "5a9a063e-bd69-4963-9aea-1131964c72f6"
          },
          "gameName": {
            "S": "Rubber Bandits"
          },
          "platform": {
            "S": "Xbox One"
          },
          "gameURL": {
            "S": "https://www.trueachievements.com/game/Rubber-Bandits/achievements?gamerid=428021"
          },
          "achievementsWonNoDlc": {
            "N": "0"
          },
          "maxAchievementsNoDlc": {
            "N": "19"
          },
          "achievementsWonIncludeDlc": {
            "N": "0"
          },
          "maxAchievementsIncludeDlc": {
            "N": "19"
          },
          "gamerScoreWonNoDlc": {
            "N": "0"
          },
          "maxGamerScoreNoDlc": {
            "N": "1000"
          },
          "gamerScoreWonIncludeDlc": {
            "N": "0"
          },
          "maxGamerScoreIncludeDlc": {
            "N": "1000"
          },
          "trueAchievementWonNoDlc": {
            "N": "0"
          },
          "maxTrueAchievementNoDlc": {
            "N": "1968"
          },
          "trueAchievementWonIncludeDlc": {
            "N": "0"
          },
          "maxTrueAchievementIncludeDlc": {
            "N": "1968"
          },
          "myCompletionPercentage": {
            "N": "0"
          },
          "completionDate": {
            "S": ""
          },
          "challengesWon": {
            "N": "0"
          },
          "maxChallenges": {
            "N": "0"
          },
          "hoursPlayed": {
            "N": "0"
          },
          "myRating": {
            "N": "0"
          },
          "siteRating": {
            "N": "3.06"
          },
          "myRatio": {
            "N": "0.0"
          },
          "siteRatio": {
            "N": "1.97"
          },
          "ownershipStatus": {
            "S": "Xbox Game Pass"
          },
          "playStatus": {
            "S": ""
          },
          "format": {
            "S": "Digital"
          },
          "completionEstimate": {
            "S": "1-2 hours"
          },
          "walkthrough": {
            "S": "https://www.trueachievements.com/game/Rubber-Bandits/walkthrough"
          },
          "gameNotes": {
            "S": "None"
          },
          "contestStatus": {
            "S": "Not for contests"
          }
        }
      }
    },
    {
      "PutRequest": {
        "Item": {
          "uniqueId": {
            "S": "17faf2e6-c9ae-471b-b854-e2d9e8e5d0c7"
          },
          "gameName": {
            "S": "Rune Factory 4 Special"
          },
          "platform": {
            "S": "Xbox One"
          },
          "gameURL": {
            "S": "https://www.trueachievements.com/game/Rune-Factory-4-Special/achievements?gamerid=428021"
          },
          "achievementsWonNoDlc": {
            "N": "0"
          },
          "maxAchievementsNoDlc": {
            "N": "38"
          },
          "achievementsWonIncludeDlc": {
            "N": "0"
          },
          "maxAchievementsIncludeDlc": {
            "N": "38"
          },
          "gamerScoreWonNoDlc": {
            "N": "0"
          },
          "maxGamerScoreNoDlc": {
            "N": "1000"
          },
          "gamerScoreWonIncludeDlc": {
            "N": "0"
          },
          "maxGamerScoreIncludeDlc": {
            "N": "1000"
          },
          "trueAchievementWonNoDlc": {
            "N": "0"
          },
          "maxTrueAchievementNoDlc": {
            "N": "5726"
          },
          "trueAchievementWonIncludeDlc": {
            "N": "0"
          },
          "maxTrueAchievementIncludeDlc": {
            "N": "5726"
          },
          "myCompletionPercentage": {
            "N": "0"
          },
          "completionDate": {
            "S": ""
          },
          "challengesWon": {
            "N": "0"
          },
          "maxChallenges": {
            "N": "0"
          },
          "hoursPlayed": {
            "N": "0"
          },
          "myRating": {
            "N": "0"
          },
          "siteRating": {
            "N": "4.22"
          },
          "myRatio": {
            "N": "0.0"
          },
          "siteRatio": {
            "N": "5.73"
          },
          "ownershipStatus": {
            "S": "Xbox Game Pass"
          },
          "playStatus": {
            "S": ""
          },
          "format": {
            "S": "Digital"
          },
          "completionEstimate": {
            "S": "150-200 hours"
          },
          "walkthrough": {
            "S": ""
          },
          "gameNotes": {
            "S": "None"
          },
          "contestStatus": {
            "S": "Not for contests"
          }
        }
      }
    },
    {
      "PutRequest": {
        "Item": {
          "uniqueId": {
            "S": "5118df9a-5bfc-40ea-a2cf-06f660b19c1d"
          },
          "gameName": {
            "S": "Rush: A Disney Pixar Adventure"
          },
          "platform": {
            "S": "Xbox One"
          },
          "gameURL": {
            "S": "https://www.trueachievements.com/game/Rush-A-Disney-Pixar-Adventure/achievements?gamerid=428021"
          },
          "achievementsWonNoDlc": {
            "N": "0"
          },
          "maxAchievementsNoDlc": {
            "N": "50"
          },
          "achievementsWonIncludeDlc": {
            "N": "0"
          },
          "maxAchievementsIncludeDlc": {
            "N": "50"
          },
          "gamerScoreWonNoDlc": {
            "N": "0"
          },
          "maxGamerScoreNoDlc": {
            "N": "1000"
          },
          "gamerScoreWonIncludeDlc": {
            "N": "0"
          },
          "maxGamerScoreIncludeDlc": {
            "N": "1000"
          },
          "trueAchievementWonNoDlc": {
            "N": "0"
          },
          "maxTrueAchievementNoDlc": {
            "N": "3365"
          },
          "trueAchievementWonIncludeDlc": {
            "N": "0"
          },
          "maxTrueAchievementIncludeDlc": {
            "N": "3365"
          },
          "myCompletionPercentage": {
            "N": "0"
          },
          "completionDate": {
            "S": ""
          },
          "challengesWon": {
            "N": "0"
          },
          "maxChallenges": {
            "N": "0"
          },
          "hoursPlayed": {
            "N": "0"
          },
          "myRating": {
            "N": "0"
          },
          "siteRating": {
            "N": "2.86"
          },
          "myRatio": {
            "N": "0.0"
          },
          "siteRatio": {
            "N": "3.37"
          },
          "ownershipStatus": {
            "S": "Xbox Game Pass"
          },
          "playStatus": {
            "S": ""
          },
          "format": {
            "S": ""
          },
          "completionEstimate": {
            "S": "15-20 hours"
          },
          "walkthrough": {
            "S": "https://www.trueachievements.com/game/Rush-A-Disney-Pixar-Adventure/walkthrough"
          },
          "gameNotes": {
            "S": "None"
          },
          "contestStatus": {
            "S": "For contests"
          }
        }
      }
    },
    {
      "PutRequest": {
        "Item": {
          "uniqueId": {
            "S": "942c18a8-31d9-4090-b1aa-6cad931412f9"
          },
          "gameName": {
            "S": "Ryse: Son of Rome"
          },
          "platform": {
            "S": "Xbox One"
          },
          "gameURL": {
            "S": "https://www.trueachievements.com/game/Ryse-Son-of-Rome/achievements?gamerid=428021"
          },
          "achievementsWonNoDlc": {
            "N": "56"
          },
          "maxAchievementsNoDlc": {
            "N": "58"
          },
          "achievementsWonIncludeDlc": {
            "N": "68"
          },
          "maxAchievementsIncludeDlc": {
            "N": "76"
          },
          "gamerScoreWonNoDlc": {
            "N": "970"
          },
          "maxGamerScoreNoDlc": {
            "N": "1000"
          },
          "gamerScoreWonIncludeDlc": {
            "N": "1620"
          },
          "maxGamerScoreIncludeDlc": {
            "N": "2000"
          },
          "trueAchievementWonNoDlc": {
            "N": "1819"
          },
          "maxTrueAchievementNoDlc": {
            "N": "2003"
          },
          "trueAchievementWonIncludeDlc": {
            "N": "3245"
          },
          "maxTrueAchievementIncludeDlc": {
            "N": "4925"
          },
          "myCompletionPercentage": {
            "N": "89"
          },
          "completionDate": {
            "S": ""
          },
          "challengesWon": {
            "N": "1"
          },
          "maxChallenges": {
            "N": "8"
          },
          "hoursPlayed": {
            "N": "41"
          },
          "myRating": {
            "N": "0"
          },
          "siteRating": {
            "N": "3.94"
          },
          "myRatio": {
            "N": "2.0"
          },
          "siteRatio": {
            "N": "2.46"
          },
          "ownershipStatus": {
            "S": "Owned"
          },
          "playStatus": {
            "S": ""
          },
          "format": {
            "S": ""
          },
          "completionEstimate": {
            "S": "40-50 hours"
          },
          "walkthrough": {
            "S": "https://www.trueachievements.com/game/Ryse-Son-of-Rome/walkthrough"
          },
          "gameNotes": {
            "S": "None"
          },
          "contestStatus": {
            "S": "Not for contests"
          }
        }
      }
    },
    {
      "PutRequest": {
        "Item": {
          "uniqueId": {
            "S": "8fae7d10-087d-4a87-aa33-ad1e575bbe75"
          },
          "gameName": {
            "S": "Saints Row (2006)"
          },
          "platform": {
            "S": "Xbox 360"
          },
          "gameURL": {
            "S": "https://www.trueachievements.com/game/Saints-Row-Xbox-360/achievements?gamerid=428021"
          },
          "achievementsWonNoDlc": {
            "N": "14"
          },
          "maxAchievementsNoDlc": {
            "N": "43"
          },
          "achievementsWonIncludeDlc": {
            "N": "14"
          },
          "maxAchievementsIncludeDlc": {
            "N": "43"
          },
          "gamerScoreWonNoDlc": {
            "N": "410"
          },
          "maxGamerScoreNoDlc": {
            "N": "1000"
          },
          "gamerScoreWonIncludeDlc": {
            "N": "410"
          },
          "maxGamerScoreIncludeDlc": {
            "N": "1000"
          },
          "trueAchievementWonNoDlc": {
            "N": "704"
          },
          "maxTrueAchievementNoDlc": {
            "N": "3606"
          },
          "trueAchievementWonIncludeDlc": {
            "N": "704"
          },
          "maxTrueAchievementIncludeDlc": {
            "N": "3606"
          },
          "myCompletionPercentage": {
            "N": "33"
          },
          "completionDate": {
            "S": ""
          },
          "challengesWon": {
            "N": "0"
          },
          "maxChallenges": {
            "N": "0"
          },
          "hoursPlayed": {
            "N": "0"
          },
          "myRating": {
            "N": "0"
          },
          "siteRating": {
            "N": "3.5"
          },
          "myRatio": {
            "N": "1.72"
          },
          "siteRatio": {
            "N": "3.61"
          },
          "ownershipStatus": {
            "S": "Owned"
          },
          "playStatus": {
            "S": ""
          },
          "format": {
            "S": "Disc"
          },
          "completionEstimate": {
            "S": "60-80 hours"
          },
          "walkthrough": {
            "S": "https://www.trueachievements.com/game/Saints-Row/walkthrough"
          },
          "gameNotes": {
            "S": "None"
          },
          "contestStatus": {
            "S": "For contests"
          }
        }
      }
    },
    {
      "PutRequest": {
        "Item": {
          "uniqueId": {
            "S": "c8d2c94f-4cdc-43fb-8e5e-ad6ddbeef7eb"
          },
          "gameName": {
            "S": "Saints Row 2"
          },
          "platform": {
            "S": "Xbox 360"
          },
          "gameURL": {
            "S": "https://www.trueachievements.com/game/Saints-Row-2/achievements?gamerid=428021"
          },
          "achievementsWonNoDlc": {
            "N": "4"
          },
          "maxAchievementsNoDlc": {
            "N": "50"
          },
          "achievementsWonIncludeDlc": {
            "N": "4"
          },
          "maxAchievementsIncludeDlc": {
            "N": "60"
          },
          "gamerScoreWonNoDlc": {
            "N": "95"
          },
          "maxGamerScoreNoDlc": {
            "N": "1000"
          },
          "gamerScoreWonIncludeDlc": {
            "N": "95"
          },
          "maxGamerScoreIncludeDlc": {
            "N": "1250"
          },
          "trueAchievementWonNoDlc": {
            "N": "120"
          },
          "maxTrueAchievementNoDlc": {
            "N": "2835"
          },
          "trueAchievementWonIncludeDlc": {
            "N": "120"
          },
          "maxTrueAchievementIncludeDlc": {
            "N": "3493"
          },
          "myCompletionPercentage": {
            "N": "8"
          },
          "completionDate": {
            "S": ""
          },
          "challengesWon": {
            "N": "0"
          },
          "maxChallenges": {
            "N": "0"
          },
          "hoursPlayed": {
            "N": "0"
          },
          "myRating": {
            "N": "0"
          },
          "siteRating": {
            "N": "4.03"
          },
          "myRatio": {
            "N": "1.26"
          },
          "siteRatio": {
            "N": "2.79"
          },
          "ownershipStatus": {
            "S": "Owned"
          },
          "playStatus": {
            "S": ""
          },
          "format": {
            "S": ""
          },
          "completionEstimate": {
            "S": "80-100 hours"
          },
          "walkthrough": {
            "S": "https://www.trueachievements.com/game/Saints-Row-2/walkthrough"
          },
          "gameNotes": {
            "S": "None"
          },
          "contestStatus": {
            "S": "For contests"
          }
        }
      }
    },
    {
      "PutRequest": {
        "Item": {
          "uniqueId": {
            "S": "1bd96a56-7e39-45ac-90c1-090402e95c9d"
          },
          "gameName": {
            "S": "Saints Row: The Third"
          },
          "platform": {
            "S": "Xbox 360"
          },
          "gameURL": {
            "S": "https://www.trueachievements.com/game/Saints-Row-The-Third/achievements?gamerid=428021"
          },
          "achievementsWonNoDlc": {
            "N": "7"
          },
          "maxAchievementsNoDlc": {
            "N": "50"
          },
          "achievementsWonIncludeDlc": {
            "N": "8"
          },
          "maxAchievementsIncludeDlc": {
            "N": "80"
          },
          "gamerScoreWonNoDlc": {
            "N": "100"
          },
          "maxGamerScoreNoDlc": {
            "N": "1000"
          },
          "gamerScoreWonIncludeDlc": {
            "N": "110"
          },
          "maxGamerScoreIncludeDlc": {
            "N": "1300"
          },
          "trueAchievementWonNoDlc": {
            "N": "119"
          },
          "maxTrueAchievementNoDlc": {
            "N": "1682"
          },
          "trueAchievementWonIncludeDlc": {
            "N": "136"
          },
          "maxTrueAchievementIncludeDlc": {
            "N": "2218"
          },
          "myCompletionPercentage": {
            "N": "13"
          },
          "completionDate": {
            "S": ""
          },
          "challengesWon": {
            "N": "0"
          },
          "maxChallenges": {
            "N": "0"
          },
          "hoursPlayed": {
            "N": "0"
          },
          "myRating": {
            "N": "0"
          },
          "siteRating": {
            "N": "4.13"
          },
          "myRatio": {
            "N": "1.24"
          },
          "siteRatio": {
            "N": "1.71"
          },
          "ownershipStatus": {
            "S": "Owned"
          },
          "playStatus": {
            "S": ""
          },
          "format": {
            "S": ""
          },
          "completionEstimate": {
            "S": "30-35 hours"
          },
          "walkthrough": {
            "S": "https://www.trueachievements.com/game/Saints-Row-The-Third/walkthrough"
          },
          "gameNotes": {
            "S": "None"
          },
          "contestStatus": {
            "S": "For contests"
          }
        }
      }
    },
    {
      "PutRequest": {
        "Item": {
          "uniqueId": {
            "S": "f3968bfc-98d8-4412-a648-10a05f48ba04"
          },
          "gameName": {
            "S": "Saints Row: The Third Remastered"
          },
          "platform": {
            "S": "Xbox One"
          },
          "gameURL": {
            "S": "https://www.trueachievements.com/game/Saints-Row-The-Third-Remastered/achievements?gamerid=428021"
          },
          "achievementsWonNoDlc": {
            "N": "2"
          },
          "maxAchievementsNoDlc": {
            "N": "79"
          },
          "achievementsWonIncludeDlc": {
            "N": "2"
          },
          "maxAchievementsIncludeDlc": {
            "N": "79"
          },
          "gamerScoreWonNoDlc": {
            "N": "25"
          },
          "maxGamerScoreNoDlc": {
            "N": "1290"
          },
          "gamerScoreWonIncludeDlc": {
            "N": "25"
          },
          "maxGamerScoreIncludeDlc": {
            "N": "1290"
          },
          "trueAchievementWonNoDlc": {
            "N": "25"
          },
          "maxTrueAchievementNoDlc": {
            "N": "2653"
          },
          "trueAchievementWonIncludeDlc": {
            "N": "25"
          },
          "maxTrueAchievementIncludeDlc": {
            "N": "2653"
          },
          "myCompletionPercentage": {
            "N": "3"
          },
          "completionDate": {
            "S": ""
          },
          "challengesWon": {
            "N": "0"
          },
          "maxChallenges": {
            "N": "0"
          },
          "hoursPlayed": {
            "N": "1"
          },
          "myRating": {
            "N": "0"
          },
          "siteRating": {
            "N": "4.16"
          },
          "myRatio": {
            "N": "1.01"
          },
          "siteRatio": {
            "N": "2.06"
          },
          "ownershipStatus": {
            "S": "Owned"
          },
          "playStatus": {
            "S": "Playing now"
          },
          "format": {
            "S": ""
          },
          "completionEstimate": {
            "S": "30-35 hours"
          },
          "walkthrough": {
            "S": ""
          },
          "gameNotes": {
            "S": "None"
          },
          "contestStatus": {
            "S": "For contests"
          }
        }
      }
    },
    {
      "PutRequest": {
        "Item": {
          "uniqueId": {
            "S": "1a3216b0-1a32-4411-b008-8fba582f2856"
          },
          "gameName": {
            "S": "Samurai Warriors 2"
          },
          "platform": {
            "S": "Xbox 360"
          },
          "gameURL": {
            "S": "https://www.trueachievements.com/game/Samurai-Warriors-2/achievements?gamerid=428021"
          },
          "achievementsWonNoDlc": {
            "N": "1"
          },
          "maxAchievementsNoDlc": {
            "N": "21"
          },
          "achievementsWonIncludeDlc": {
            "N": "1"
          },
          "maxAchievementsIncludeDlc": {
            "N": "29"
          },
          "gamerScoreWonNoDlc": {
            "N": "50"
          },
          "maxGamerScoreNoDlc": {
            "N": "1000"
          },
          "gamerScoreWonIncludeDlc": {
            "N": "50"
          },
          "maxGamerScoreIncludeDlc": {
            "N": "1250"
          },
          "trueAchievementWonNoDlc": {
            "N": "54"
          },
          "maxTrueAchievementNoDlc": {
            "N": "1359"
          },
          "trueAchievementWonIncludeDlc": {
            "N": "54"
          },
          "maxTrueAchievementIncludeDlc": {
            "N": "1797"
          },
          "myCompletionPercentage": {
            "N": "5"
          },
          "completionDate": {
            "S": ""
          },
          "challengesWon": {
            "N": "0"
          },
          "maxChallenges": {
            "N": "0"
          },
          "hoursPlayed": {
            "N": "0"
          },
          "myRating": {
            "N": "0"
          },
          "siteRating": {
            "N": "3.38"
          },
          "myRatio": {
            "N": "1.09"
          },
          "siteRatio": {
            "N": "1.44"
          },
          "ownershipStatus": {
            "S": "Owned"
          },
          "playStatus": {
            "S": ""
          },
          "format": {
            "S": ""
          },
          "completionEstimate": {
            "S": "40-50 hours"
          },
          "walkthrough": {
            "S": ""
          },
          "gameNotes": {
            "S": "None"
          },
          "contestStatus": {
            "S": "For contests"
          }
        }
      }
    },
    {
      "PutRequest": {
        "Item": {
          "uniqueId": {
            "S": "749db778-f3d1-4c06-85a2-ffe45fc9a1f2"
          },
          "gameName": {
            "S": "Saw"
          },
          "platform": {
            "S": "Xbox 360"
          },
          "gameURL": {
            "S": "https://www.trueachievements.com/game/Saw/achievements?gamerid=428021"
          },
          "achievementsWonNoDlc": {
            "N": "29"
          },
          "maxAchievementsNoDlc": {
            "N": "46"
          },
          "achievementsWonIncludeDlc": {
            "N": "29"
          },
          "maxAchievementsIncludeDlc": {
            "N": "46"
          },
          "gamerScoreWonNoDlc": {
            "N": "470"
          },
          "maxGamerScoreNoDlc": {
            "N": "1000"
          },
          "gamerScoreWonIncludeDlc": {
            "N": "470"
          },
          "maxGamerScoreIncludeDlc": {
            "N": "1000"
          },
          "trueAchievementWonNoDlc": {
            "N": "533"
          },
          "maxTrueAchievementNoDlc": {
            "N": "1294"
          },
          "trueAchievementWonIncludeDlc": {
            "N": "533"
          },
          "maxTrueAchievementIncludeDlc": {
            "N": "1294"
          },
          "myCompletionPercentage": {
            "N": "63"
          },
          "completionDate": {
            "S": ""
          },
          "challengesWon": {
            "N": "0"
          },
          "maxChallenges": {
            "N": "0"
          },
          "hoursPlayed": {
            "N": "0"
          },
          "myRating": {
            "N": "0"
          },
          "siteRating": {
            "N": "3.02"
          },
          "myRatio": {
            "N": "1.13"
          },
          "siteRatio": {
            "N": "1.3"
          },
          "ownershipStatus": {
            "S": "Owned"
          },
          "playStatus": {
            "S": ""
          },
          "format": {
            "S": ""
          },
          "completionEstimate": {
            "S": "8-10 hours"
          },
          "walkthrough": {
            "S": "https://www.trueachievements.com/game/Saw/walkthrough"
          },
          "gameNotes": {
            "S": "None"
          },
          "contestStatus": {
            "S": "For contests"
          }
        }
      }
    },
    {
      "PutRequest": {
        "Item": {
          "uniqueId": {
            "S": "9c6975fa-6fdc-449f-adef-da54ff0d1174"
          },
          "gameName": {
            "S": "Scarlet Nexus"
          },
          "platform": {
            "S": "Xbox One"
          },
          "gameURL": {
            "S": "https://www.trueachievements.com/game/Scarlet-Nexus/achievements?gamerid=428021"
          },
          "achievementsWonNoDlc": {
            "N": "7"
          },
          "maxAchievementsNoDlc": {
            "N": "53"
          },
          "achievementsWonIncludeDlc": {
            "N": "7"
          },
          "maxAchievementsIncludeDlc": {
            "N": "53"
          },
          "gamerScoreWonNoDlc": {
            "N": "95"
          },
          "maxGamerScoreNoDlc": {
            "N": "1000"
          },
          "gamerScoreWonIncludeDlc": {
            "N": "95"
          },
          "maxGamerScoreIncludeDlc": {
            "N": "1000"
          },
          "trueAchievementWonNoDlc": {
            "N": "144"
          },
          "maxTrueAchievementNoDlc": {
            "N": "3080"
          },
          "trueAchievementWonIncludeDlc": {
            "N": "144"
          },
          "maxTrueAchievementIncludeDlc": {
            "N": "3080"
          },
          "myCompletionPercentage": {
            "N": "13"
          },
          "completionDate": {
            "S": ""
          },
          "challengesWon": {
            "N": "0"
          },
          "maxChallenges": {
            "N": "0"
          },
          "hoursPlayed": {
            "N": "4"
          },
          "myRating": {
            "N": "0"
          },
          "siteRating": {
            "N": "3.97"
          },
          "myRatio": {
            "N": "1.52"
          },
          "siteRatio": {
            "N": "3.08"
          },
          "ownershipStatus": {
            "S": "Owned"
          },
          "playStatus": {
            "S": "Playing now"
          },
          "format": {
            "S": ""
          },
          "completionEstimate": {
            "S": "60-80 hours"
          },
          "walkthrough": {
            "S": ""
          },
          "gameNotes": {
            "S": "None"
          },
          "contestStatus": {
            "S": "Not for contests"
          }
        }
      }
    },
    {
      "PutRequest": {
        "Item": {
          "uniqueId": {
            "S": "a91a1a56-9737-4d33-a967-356131ece595"
          },
          "gameName": {
            "S": "Scorn"
          },
          "platform": {
            "S": "Xbox Series X|S"
          },
          "gameURL": {
            "S": "https://www.trueachievements.com/game/Scorn/achievements?gamerid=428021"
          },
          "achievementsWonNoDlc": {
            "N": "0"
          },
          "maxAchievementsNoDlc": {
            "N": "12"
          },
          "achievementsWonIncludeDlc": {
            "N": "0"
          },
          "maxAchievementsIncludeDlc": {
            "N": "12"
          },
          "gamerScoreWonNoDlc": {
            "N": "0"
          },
          "maxGamerScoreNoDlc": {
            "N": "1000"
          },
          "gamerScoreWonIncludeDlc": {
            "N": "0"
          },
          "maxGamerScoreIncludeDlc": {
            "N": "1000"
          },
          "trueAchievementWonNoDlc": {
            "N": "0"
          },
          "maxTrueAchievementNoDlc": {
            "N": "1443"
          },
          "trueAchievementWonIncludeDlc": {
            "N": "0"
          },
          "maxTrueAchievementIncludeDlc": {
            "N": "1443"
          },
          "myCompletionPercentage": {
            "N": "0"
          },
          "completionDate": {
            "S": ""
          },
          "challengesWon": {
            "N": "0"
          },
          "maxChallenges": {
            "N": "0"
          },
          "hoursPlayed": {
            "N": "0"
          },
          "myRating": {
            "N": "0"
          },
          "siteRating": {
            "N": "3.32"
          },
          "myRatio": {
            "N": "0.0"
          },
          "siteRatio": {
            "N": "1.44"
          },
          "ownershipStatus": {
            "S": "Xbox Game Pass"
          },
          "playStatus": {
            "S": ""
          },
          "format": {
            "S": "Digital"
          },
          "completionEstimate": {
            "S": "5-6 hours"
          },
          "walkthrough": {
            "S": "https://www.trueachievements.com/game/Scorn/walkthrough"
          },
          "gameNotes": {
            "S": "None"
          },
          "contestStatus": {
            "S": "Not for contests"
          }
        }
      }
    },
    {
      "PutRequest": {
        "Item": {
          "uniqueId": {
            "S": "3694fcbd-0850-42f7-89b2-e8c8c99a7e29"
          },
          "gameName": {
            "S": "ScreamRide"
          },
          "platform": {
            "S": "Xbox One"
          },
          "gameURL": {
            "S": "https://www.trueachievements.com/game/ScreamRide/achievements?gamerid=428021"
          },
          "achievementsWonNoDlc": {
            "N": "0"
          },
          "maxAchievementsNoDlc": {
            "N": "47"
          },
          "achievementsWonIncludeDlc": {
            "N": "0"
          },
          "maxAchievementsIncludeDlc": {
            "N": "47"
          },
          "gamerScoreWonNoDlc": {
            "N": "0"
          },
          "maxGamerScoreNoDlc": {
            "N": "1000"
          },
          "gamerScoreWonIncludeDlc": {
            "N": "0"
          },
          "maxGamerScoreIncludeDlc": {
            "N": "1000"
          },
          "trueAchievementWonNoDlc": {
            "N": "0"
          },
          "maxTrueAchievementNoDlc": {
            "N": "13592"
          },
          "trueAchievementWonIncludeDlc": {
            "N": "0"
          },
          "maxTrueAchievementIncludeDlc": {
            "N": "13592"
          },
          "myCompletionPercentage": {
            "N": "0"
          },
          "completionDate": {
            "S": ""
          },
          "challengesWon": {
            "N": "0"
          },
          "maxChallenges": {
            "N": "0"
          },
          "hoursPlayed": {
            "N": "0"
          },
          "myRating": {
            "N": "0"
          },
          "siteRating": {
            "N": "3.01"
          },
          "myRatio": {
            "N": "0.0"
          },
          "siteRatio": {
            "N": "13.59"
          },
          "ownershipStatus": {
            "S": "Xbox Game Pass"
          },
          "playStatus": {
            "S": ""
          },
          "format": {
            "S": ""
          },
          "completionEstimate": {
            "S": "50-60 hours"
          },
          "walkthrough": {
            "S": "https://www.trueachievements.com/game/ScreamRide-Xbox-One/walkthrough"
          },
          "gameNotes": {
            "S": "None"
          },
          "contestStatus": {
            "S": "Not for contests"
          }
        }
      }
    },
    {
      "PutRequest": {
        "Item": {
          "uniqueId": {
            "S": "9724ed56-9bc1-4ae9-9534-f949f3b72766"
          },
          "gameName": {
            "S": "SD Gundam Battle Alliance"
          },
          "platform": {
            "S": "Xbox One"
          },
          "gameURL": {
            "S": "https://www.trueachievements.com/game/SD-Gundam-Battle-Alliance/achievements?gamerid=428021"
          },
          "achievementsWonNoDlc": {
            "N": "0"
          },
          "maxAchievementsNoDlc": {
            "N": "43"
          },
          "achievementsWonIncludeDlc": {
            "N": "0"
          },
          "maxAchievementsIncludeDlc": {
            "N": "43"
          },
          "gamerScoreWonNoDlc": {
            "N": "0"
          },
          "maxGamerScoreNoDlc": {
            "N": "1000"
          },
          "gamerScoreWonIncludeDlc": {
            "N": "0"
          },
          "maxGamerScoreIncludeDlc": {
            "N": "1000"
          },
          "trueAchievementWonNoDlc": {
            "N": "0"
          },
          "maxTrueAchievementNoDlc": {
            "N": "2875"
          },
          "trueAchievementWonIncludeDlc": {
            "N": "0"
          },
          "maxTrueAchievementIncludeDlc": {
            "N": "2875"
          },
          "myCompletionPercentage": {
            "N": "0"
          },
          "completionDate": {
            "S": ""
          },
          "challengesWon": {
            "N": "0"
          },
          "maxChallenges": {
            "N": "0"
          },
          "hoursPlayed": {
            "N": "0"
          },
          "myRating": {
            "N": "0"
          },
          "siteRating": {
            "N": "3.48"
          },
          "myRatio": {
            "N": "0.0"
          },
          "siteRatio": {
            "N": "2.88"
          },
          "ownershipStatus": {
            "S": "Xbox Game Pass"
          },
          "playStatus": {
            "S": ""
          },
          "format": {
            "S": "Digital"
          },
          "completionEstimate": {
            "S": "25-30 hours"
          },
          "walkthrough": {
            "S": ""
          },
          "gameNotes": {
            "S": "None"
          },
          "contestStatus": {
            "S": "Not for contests"
          }
        }
      }
    },
    {
      "PutRequest": {
        "Item": {
          "uniqueId": {
            "S": "933a277b-c582-4ab7-addb-bbbdf297b7d0"
          },
          "gameName": {
            "S": "Sea of Solitude"
          },
          "platform": {
            "S": "Xbox One"
          },
          "gameURL": {
            "S": "https://www.trueachievements.com/game/Sea-of-Solitude/achievements?gamerid=428021"
          },
          "achievementsWonNoDlc": {
            "N": "0"
          },
          "maxAchievementsNoDlc": {
            "N": "22"
          },
          "achievementsWonIncludeDlc": {
            "N": "0"
          },
          "maxAchievementsIncludeDlc": {
            "N": "22"
          },
          "gamerScoreWonNoDlc": {
            "N": "0"
          },
          "maxGamerScoreNoDlc": {
            "N": "1000"
          },
          "gamerScoreWonIncludeDlc": {
            "N": "0"
          },
          "maxGamerScoreIncludeDlc": {
            "N": "1000"
          },
          "trueAchievementWonNoDlc": {
            "N": "0"
          },
          "maxTrueAchievementNoDlc": {
            "N": "1946"
          },
          "trueAchievementWonIncludeDlc": {
            "N": "0"
          },
          "maxTrueAchievementIncludeDlc": {
            "N": "1946"
          },
          "myCompletionPercentage": {
            "N": "0"
          },
          "completionDate": {
            "S": ""
          },
          "challengesWon": {
            "N": "0"
          },
          "maxChallenges": {
            "N": "0"
          },
          "hoursPlayed": {
            "N": "0"
          },
          "myRating": {
            "N": "0"
          },
          "siteRating": {
            "N": "3.58"
          },
          "myRatio": {
            "N": "0.0"
          },
          "siteRatio": {
            "N": "1.95"
          },
          "ownershipStatus": {
            "S": "EA Play"
          },
          "playStatus": {
            "S": ""
          },
          "format": {
            "S": "Digital"
          },
          "completionEstimate": {
            "S": "5-6 hours"
          },
          "walkthrough": {
            "S": ""
          },
          "gameNotes": {
            "S": "None"
          },
          "contestStatus": {
            "S": "For contests"
          }
        }
      }
    },
    {
      "PutRequest": {
        "Item": {
          "uniqueId": {
            "S": "3ecc1ebb-933e-4c6c-99a7-69059dc07358"
          },
          "gameName": {
            "S": "Sea of Stars"
          },
          "platform": {
            "S": "Xbox One"
          },
          "gameURL": {
            "S": "https://www.trueachievements.com/game/Sea-of-Stars/achievements?gamerid=428021"
          },
          "achievementsWonNoDlc": {
            "N": "0"
          },
          "maxAchievementsNoDlc": {
            "N": "42"
          },
          "achievementsWonIncludeDlc": {
            "N": "0"
          },
          "maxAchievementsIncludeDlc": {
            "N": "42"
          },
          "gamerScoreWonNoDlc": {
            "N": "0"
          },
          "maxGamerScoreNoDlc": {
            "N": "1000"
          },
          "gamerScoreWonIncludeDlc": {
            "N": "0"
          },
          "maxGamerScoreIncludeDlc": {
            "N": "1000"
          },
          "trueAchievementWonNoDlc": {
            "N": "0"
          },
          "maxTrueAchievementNoDlc": {
            "N": "3964"
          },
          "trueAchievementWonIncludeDlc": {
            "N": "0"
          },
          "maxTrueAchievementIncludeDlc": {
            "N": "3964"
          },
          "myCompletionPercentage": {
            "N": "0"
          },
          "completionDate": {
            "S": ""
          },
          "challengesWon": {
            "N": "0"
          },
          "maxChallenges": {
            "N": "0"
          },
          "hoursPlayed": {
            "N": "0"
          },
          "myRating": {
            "N": "0"
          },
          "siteRating": {
            "N": "4.62"
          },
          "myRatio": {
            "N": "0.0"
          },
          "siteRatio": {
            "N": "3.96"
          },
          "ownershipStatus": {
            "S": "Xbox Game Pass"
          },
          "playStatus": {
            "S": ""
          },
          "format": {
            "S": "Digital"
          },
          "completionEstimate": {
            "S": "40-50 hours"
          },
          "walkthrough": {
            "S": ""
          },
          "gameNotes": {
            "S": "None"
          },
          "contestStatus": {
            "S": "Not for contests"
          }
        }
      }
    },
    {
      "PutRequest": {
        "Item": {
          "uniqueId": {
            "S": "0df0fa53-b89c-4419-992a-2df2d3583ebd"
          },
          "gameName": {
            "S": "Sea of Thieves"
          },
          "platform": {
            "S": "Xbox One"
          },
          "gameURL": {
            "S": "https://www.trueachievements.com/game/Sea-of-Thieves/achievements?gamerid=428021"
          },
          "achievementsWonNoDlc": {
            "N": "10"
          },
          "maxAchievementsNoDlc": {
            "N": "60"
          },
          "achievementsWonIncludeDlc": {
            "N": "12"
          },
          "maxAchievementsIncludeDlc": {
            "N": "230"
          },
          "gamerScoreWonNoDlc": {
            "N": "95"
          },
          "maxGamerScoreNoDlc": {
            "N": "1000"
          },
          "gamerScoreWonIncludeDlc": {
            "N": "105"
          },
          "maxGamerScoreIncludeDlc": {
            "N": "4530"
          },
          "trueAchievementWonNoDlc": {
            "N": "114"
          },
          "maxTrueAchievementNoDlc": {
            "N": "6519"
          },
          "trueAchievementWonIncludeDlc": {
            "N": "129"
          },
          "maxTrueAchievementIncludeDlc": {
            "N": "39679"
          },
          "myCompletionPercentage": {
            "N": "12"
          },
          "completionDate": {
            "S": ""
          },
          "challengesWon": {
            "N": "0"
          },
          "maxChallenges": {
            "N": "0"
          },
          "hoursPlayed": {
            "N": "7"
          },
          "myRating": {
            "N": "0"
          },
          "siteRating": {
            "N": "3.78"
          },
          "myRatio": {
            "N": "1.23"
          },
          "siteRatio": {
            "N": "8.76"
          },
          "ownershipStatus": {
            "S": "Owned"
          },
          "playStatus": {
            "S": "Playing now"
          },
          "format": {
            "S": ""
          },
          "completionEstimate": {
            "S": "1000+ hours"
          },
          "walkthrough": {
            "S": "https://www.trueachievements.com/game/Sea-of-Thieves/walkthrough"
          },
          "gameNotes": {
            "S": "None"
          },
          "contestStatus": {
            "S": "For contests"
          }
        }
      }
    },
    {
      "PutRequest": {
        "Item": {
          "uniqueId": {
            "S": "553a40dd-be98-4a89-8310-2903f95c56da"
          },
          "gameName": {
            "S": "Sea Salt"
          },
          "platform": {
            "S": "Xbox One"
          },
          "gameURL": {
            "S": "https://www.trueachievements.com/game/Sea-Salt/achievements?gamerid=428021"
          },
          "achievementsWonNoDlc": {
            "N": "4"
          },
          "maxAchievementsNoDlc": {
            "N": "19"
          },
          "achievementsWonIncludeDlc": {
            "N": "4"
          },
          "maxAchievementsIncludeDlc": {
            "N": "19"
          },
          "gamerScoreWonNoDlc": {
            "N": "100"
          },
          "maxGamerScoreNoDlc": {
            "N": "1000"
          },
          "gamerScoreWonIncludeDlc": {
            "N": "100"
          },
          "maxGamerScoreIncludeDlc": {
            "N": "1000"
          },
          "trueAchievementWonNoDlc": {
            "N": "167"
          },
          "maxTrueAchievementNoDlc": {
            "N": "4077"
          },
          "trueAchievementWonIncludeDlc": {
            "N": "167"
          },
          "maxTrueAchievementIncludeDlc": {
            "N": "4077"
          },
          "myCompletionPercentage": {
            "N": "21"
          },
          "completionDate": {
            "S": ""
          },
          "challengesWon": {
            "N": "0"
          },
          "maxChallenges": {
            "N": "0"
          },
          "hoursPlayed": {
            "N": "2"
          },
          "myRating": {
            "N": "0"
          },
          "siteRating": {
            "N": "3.18"
          },
          "myRatio": {
            "N": "1.68"
          },
          "siteRatio": {
            "N": "4.08"
          },
          "ownershipStatus": {
            "S": "No longer have"
          },
          "playStatus": {
            "S": ""
          },
          "format": {
            "S": "Digital"
          },
          "completionEstimate": {
            "S": "8-10 hours"
          },
          "walkthrough": {
            "S": ""
          },
          "gameNotes": {
            "S": "None"
          },
          "contestStatus": {
            "S": "For contests"
          }
        }
      }
    },
    {
      "PutRequest": {
        "Item": {
          "uniqueId": {
            "S": "9b0add35-3924-419e-a316-89a4ff10d82c"
          },
          "gameName": {
            "S": "Second Extinction"
          },
          "platform": {
            "S": "Xbox One"
          },
          "gameURL": {
            "S": "https://www.trueachievements.com/game/Second-Extinction/achievements?gamerid=428021"
          },
          "achievementsWonNoDlc": {
            "N": "10"
          },
          "maxAchievementsNoDlc": {
            "N": "29"
          },
          "achievementsWonIncludeDlc": {
            "N": "10"
          },
          "maxAchievementsIncludeDlc": {
            "N": "29"
          },
          "gamerScoreWonNoDlc": {
            "N": "280"
          },
          "maxGamerScoreNoDlc": {
            "N": "1000"
          },
          "gamerScoreWonIncludeDlc": {
            "N": "280"
          },
          "maxGamerScoreIncludeDlc": {
            "N": "1000"
          },
          "trueAchievementWonNoDlc": {
            "N": "611"
          },
          "maxTrueAchievementNoDlc": {
            "N": "4634"
          },
          "trueAchievementWonIncludeDlc": {
            "N": "611"
          },
          "maxTrueAchievementIncludeDlc": {
            "N": "4634"
          },
          "myCompletionPercentage": {
            "N": "34"
          },
          "completionDate": {
            "S": ""
          },
          "challengesWon": {
            "N": "0"
          },
          "maxChallenges": {
            "N": "0"
          },
          "hoursPlayed": {
            "N": "14"
          },
          "myRating": {
            "N": "0"
          },
          "siteRating": {
            "N": "3.0"
          },
          "myRatio": {
            "N": "2.18"
          },
          "siteRatio": {
            "N": "4.63"
          },
          "ownershipStatus": {
            "S": "No longer have"
          },
          "playStatus": {
            "S": ""
          },
          "format": {
            "S": "Digital"
          },
          "completionEstimate": {
            "S": "20-25 hours"
          },
          "walkthrough": {
            "S": "https://www.trueachievements.com/game/Second-Extinction/walkthrough"
          },
          "gameNotes": {
            "S": "None"
          },
          "contestStatus": {
            "S": "Not for contests"
          }
        }
      }
    },
    {
      "PutRequest": {
        "Item": {
          "uniqueId": {
            "S": "265336be-1b05-4670-a2c0-ca11bf13a779"
          },
          "gameName": {
            "S": "Serious Sam 4"
          },
          "platform": {
            "S": "Xbox Series X|S"
          },
          "gameURL": {
            "S": "https://www.trueachievements.com/game/Serious-Sam-4/achievements?gamerid=428021"
          },
          "achievementsWonNoDlc": {
            "N": "6"
          },
          "maxAchievementsNoDlc": {
            "N": "54"
          },
          "achievementsWonIncludeDlc": {
            "N": "6"
          },
          "maxAchievementsIncludeDlc": {
            "N": "54"
          },
          "gamerScoreWonNoDlc": {
            "N": "80"
          },
          "maxGamerScoreNoDlc": {
            "N": "1000"
          },
          "gamerScoreWonIncludeDlc": {
            "N": "80"
          },
          "maxGamerScoreIncludeDlc": {
            "N": "1000"
          },
          "trueAchievementWonNoDlc": {
            "N": "124"
          },
          "maxTrueAchievementNoDlc": {
            "N": "2955"
          },
          "trueAchievementWonIncludeDlc": {
            "N": "124"
          },
          "maxTrueAchievementIncludeDlc": {
            "N": "2955"
          },
          "myCompletionPercentage": {
            "N": "11"
          },
          "completionDate": {
            "S": ""
          },
          "challengesWon": {
            "N": "0"
          },
          "maxChallenges": {
            "N": "0"
          },
          "hoursPlayed": {
            "N": "1"
          },
          "myRating": {
            "N": "0"
          },
          "siteRating": {
            "N": "3.18"
          },
          "myRatio": {
            "N": "1.56"
          },
          "siteRatio": {
            "N": "2.96"
          },
          "ownershipStatus": {
            "S": "No longer have"
          },
          "playStatus": {
            "S": ""
          },
          "format": {
            "S": "Digital"
          },
          "completionEstimate": {
            "S": "8-10 hours"
          },
          "walkthrough": {
            "S": "https://www.trueachievements.com/game/Serious-Sam-4/walkthrough"
          },
          "gameNotes": {
            "S": "None"
          },
          "contestStatus": {
            "S": "Not for contests"
          }
        }
      }
    },
    {
      "PutRequest": {
        "Item": {
          "uniqueId": {
            "S": "2bfa7c71-aaae-42e7-8f79-dda019171a12"
          },
          "gameName": {
            "S": "Serious Sam: Siberian Mayhem"
          },
          "platform": {
            "S": "Xbox Series X|S"
          },
          "gameURL": {
            "S": "https://www.trueachievements.com/game/Serious-Sam-Siberian-Mayhem/achievements?gamerid=428021"
          },
          "achievementsWonNoDlc": {
            "N": "0"
          },
          "maxAchievementsNoDlc": {
            "N": "49"
          },
          "achievementsWonIncludeDlc": {
            "N": "0"
          },
          "maxAchievementsIncludeDlc": {
            "N": "49"
          },
          "gamerScoreWonNoDlc": {
            "N": "0"
          },
          "maxGamerScoreNoDlc": {
            "N": "1000"
          },
          "gamerScoreWonIncludeDlc": {
            "N": "0"
          },
          "maxGamerScoreIncludeDlc": {
            "N": "1000"
          },
          "trueAchievementWonNoDlc": {
            "N": "0"
          },
          "maxTrueAchievementNoDlc": {
            "N": "7428"
          },
          "trueAchievementWonIncludeDlc": {
            "N": "0"
          },
          "maxTrueAchievementIncludeDlc": {
            "N": "7428"
          },
          "myCompletionPercentage": {
            "N": "0"
          },
          "completionDate": {
            "S": ""
          },
          "challengesWon": {
            "N": "0"
          },
          "maxChallenges": {
            "N": "0"
          },
          "hoursPlayed": {
            "N": "0"
          },
          "myRating": {
            "N": "0"
          },
          "siteRating": {
            "N": "3.31"
          },
          "myRatio": {
            "N": "0.0"
          },
          "siteRatio": {
            "N": "7.43"
          },
          "ownershipStatus": {
            "S": "Xbox Game Pass"
          },
          "playStatus": {
            "S": ""
          },
          "format": {
            "S": "Digital"
          },
          "completionEstimate": {
            "S": ""
          },
          "walkthrough": {
            "S": ""
          },
          "gameNotes": {
            "S": "None"
          },
          "contestStatus": {
            "S": "Not for contests"
          }
        }
      }
    },
    {
      "PutRequest": {
        "Item": {
          "uniqueId": {
            "S": "cd77a739-9707-467d-bb63-13a1196467e8"
          },
          "gameName": {
            "S": "Shadow of the Tomb Raider"
          },
          "platform": {
            "S": "Xbox One"
          },
          "gameURL": {
            "S": "https://www.trueachievements.com/game/Shadow-of-the-Tomb-Raider/achievements?gamerid=428021"
          },
          "achievementsWonNoDlc": {
            "N": "52"
          },
          "maxAchievementsNoDlc": {
            "N": "63"
          },
          "achievementsWonIncludeDlc": {
            "N": "52"
          },
          "maxAchievementsIncludeDlc": {
            "N": "99"
          },
          "gamerScoreWonNoDlc": {
            "N": "870"
          },
          "maxGamerScoreNoDlc": {
            "N": "1000"
          },
          "gamerScoreWonIncludeDlc": {
            "N": "870"
          },
          "maxGamerScoreIncludeDlc": {
            "N": "1690"
          },
          "trueAchievementWonNoDlc": {
            "N": "1271"
          },
          "maxTrueAchievementNoDlc": {
            "N": "1674"
          },
          "trueAchievementWonIncludeDlc": {
            "N": "1271"
          },
          "maxTrueAchievementIncludeDlc": {
            "N": "3114"
          },
          "myCompletionPercentage": {
            "N": "83"
          },
          "completionDate": {
            "S": ""
          },
          "challengesWon": {
            "N": "0"
          },
          "maxChallenges": {
            "N": "0"
          },
          "hoursPlayed": {
            "N": "24"
          },
          "myRating": {
            "N": "0"
          },
          "siteRating": {
            "N": "4.28"
          },
          "myRatio": {
            "N": "1.46"
          },
          "siteRatio": {
            "N": "1.84"
          },
          "ownershipStatus": {
            "S": "Owned"
          },
          "playStatus": {
            "S": "Playing now"
          },
          "format": {
            "S": ""
          },
          "completionEstimate": {
            "S": "40-50 hours"
          },
          "walkthrough": {
            "S": "https://www.trueachievements.com/game/Shadow-of-the-Tomb-Raider/walkthrough"
          },
          "gameNotes": {
            "S": "None"
          },
          "contestStatus": {
            "S": "For contests"
          }
        }
      }
    }
  ]
}